transcriber/__init__.py
transcriber/message_handler/__init__.py
transcriber/message_handler/base.py
transcriber/message_handler/bytes_handler.py
transcriber/message_handler/executor.py
transcriber/message_handler/text_handler.py
transcriber/message_handler/types.py
transcriber/message_handler/websocket_runner.py
smooth_websocket_daemon-0.1.0.dist-info/METADATA
smooth_websocket_daemon-0.1.0.dist-info/WHEEL
smooth_websocket_daemon-0.1.0.dist-info/top_level.txt
smooth_websocket_daemon-0.1.0.dist-info/RECORD
